{
  "id": "beikuang",
  "name": "北荒",
  "type": "region",
  "description": "王者大陆最北端的苦寒之地，燕然诸部世代游牧于此。传说日之塔被破坏后此地变得严寒，大雪山、圣湖与一望无际的草原是北荒的标志，燕然诸部信仰苍狼图腾，等待着能统一北地的领袖降临。",
  "content": "北荒是王者大陆的最北端，寒冷的气候统治这片土地，只有夏季会略为温暖。这里绵延着大雪山和燕然诸部的圣湖，广阔的草原春夏铺满高草，冬天则为严寒所威胁。传说日之塔被破坏后此地才变得寒冷，其残余力量唤醒了大陆的意志，诸多匪夷所思的传说由此流传。燕然诸部坚定信仰苍狼图腾，期待领袖带领他们统一北地。",
  "districts": [
    {
      "name": "日之塔",
      "description": "矗立于北荒大地的高塔，传说是太古文明遗留的奇迹建筑。过去此地曾温暖如春，日之塔被破坏后才变得寒冷。日之塔残余的破坏力量唤醒了大陆的意志，使得迄今这里流传着种种匪夷所思的传说。"
    },
    {
      "name": "狼旗",
      "description": "王者大陆的最北端，大部分时间寒冷统治土地，只有夏季会略为温暖。这里绵延着大雪山和燕然诸部的圣湖。当燕然诸部遭遇战争失败或者饥荒时才会北上来此休养生息。一望无际的草原，春夏铺满高草，冬天则为严寒所威胁。这里生活着昔日太古时代大迁徙子民的后裔。他们分为无数的部落，在过往的岁月中一直与严寒和贫困抗争，而坚固的长城阻止了他们南下。这些子民们坚定不移的信仰苍狼的图腾，认为总有一天会出现领袖带领他们统一北地。"
    }
  ],
  "miracle": "",
  "leader": null,
  "members": [],
  "allies": [],
  "enemies": [],
  "status": "active",
  "tags": [
    "草原",
    "北方",
    "游牧",
    "蛮荒",
    "燕然",
    "苍狼"
  ],
  "imageUrl": "/images/factions/beikuang.jpg"
}